[
  { "url": "https://example.com/video1.mp4", "category": "ğ…ğ®ğ§ğ§ğ² ğ•ğ¢ğğğ¨" },
  { "url": "https://example.com/video1.mp4", "category": "ğˆğ¬ğ¥ğšğ¦ğ¢ğœ ğ•ğ¢ğğğ¨" },
  { "url": "https://example.com/video1.mp4", "category": "ğ’ğšğ ğ•ğ¢ğğğ¨" },
  { "url": "https://example.com/video1.mp4", "category": "ğ€ğ§ğ¢ğ¦ğ ğ•ğ¢ğğğ¨" },
  { "url": "https://example.com/video1.mp4", "category": "ğ‹ğ¨ğ…ğˆ ğ•ğ¢ğğğ¨" },
  { "url": "https://example.com/video1.mp4", "category": "ğ€ğ­ğ­ğ¢ğ­ğ®ğğ ğ•ğ¢ğğğ¨" },
  { "url": "https://example.com/video1.mp4", "category": "ğ‡ğ¨ğ«ğ§ğ² ğ•ğ¢ğğğ¨" },
  { "url": "https://example.com/video1.mp4", "category": "ğ‚ğ¨ğ®ğ©ğ¥ğ ğ•ğ¢ğğğ¨" },
  { "url": "https://example.com/video2.mp4", "category": "ğ…ğ¥ğ¨ğ°ğğ« ğ•ğ¢ğğğ¨" },
  { "url": "https://example.com/video3.mp4", "category": "ğğ¢ğ¤ğ & ğ‚ğšğ« ğ•ğ¢ğğğ¨" },
  { "url": "https://example.com/video1.mp4", "category": "" },
  { "url": "https://example.com/video1.mp4", "category": "" },
  { "url": "https://example.com/video1.mp4", "category": "" },
  { "url": "https://example.com/video1.mp4", "category": "" },
  { "url": "https://example.com/video1.mp4", "category": "" },
  { "url": "https://example.com/video1.mp4", "category": "" },
  { "url": "https://example.com/video1.mp4", "category": "" },
  { "url": "https://example.com/video1.mp4", "category": "" },
  { "url": "https://example.com/video1.mp4", "category": "" },
  { "url": "https://example.com/video1.mp4", "category": "" },
  { "url": "https://example.com/video1.mp4", "category": "" },
  { "url": "https://example.com/video1.mp4", "category": "" },
  { "url": "https://example.com/video1.mp4", "category": "" },
  { "url": "https://example.com/video1.mp4", "category": "" },
  { "url": "https://example.com/video1.mp4", "category": "" },
  { "url": "https://example.com/video1.mp4", "category": "" },
  { "url": "https://example.com/video1.mp4", "category": "" },
  { "url": "https://example.com/video1.mp4", "category": "" },
  { "url": "https://example.com/video1.mp4", "category": "" },
  { "url": "https://example.com/video1.mp4", "category": "" },
  { "url": "https://example.com/video1.mp4", "category": "" },
  { "url": "https://example.com/video1.mp4", "category": "" },
  { "url": "https://example.com/video1.mp4", "category": "" },
  { "url": "https://example.com/video1.mp4", "category": "" },
  { "url": "https://example.com/video1.mp4", "category": "" },
  { "url": "https://example.com/video1.mp4", "category": "" },
  { "url": "https://example.com/video1.mp4", "category": "" },
  { "url": "https://example.com/video1.mp4", "category": "" },
  { "url": "https://example.com/video1.mp4", "category": "" },
  { "url": "https://example.com/video1.mp4", "category": "" },
  { "url": "https://example.com/video1.mp4", "category": "" }
  ]
